pvr2image.py
pvr2img-1.1.0.dist-info/LICENSE.txt
pvr2img-1.1.0.dist-info/METADATA
pvr2img-1.1.0.dist-info/WHEEL
pvr2img-1.1.0.dist-info/top_level.txt
pvr2img-1.1.0.dist-info/RECORD
