Metadata-Version: 2.1
Name: pvr2img
Version: 1.1.0
Summary: A Python library to easily convert Dreamcast/Naomi .PVR and .PVP files to images + palettes
Home-page: https://github.com/VincentNLOBJ/pvr2image
Author: VincentNL
Author-email: VincentNL <zgoro@protonmail.com>
Project-URL: Homepage, https://github.com/VincentNLOBJ/pvr2image
Project-URL: Issues, https://github.com/VincentNLOBJ/pvr2image/issues
Classifier: Programming Language :: Python :: 3
Classifier: License :: OSI Approved :: MIT License
Classifier: Operating System :: OS Independent
Requires-Python: >=3.9
License-File: LICENSE.txt
